{
  "Truck":{
    "speed":10,
    "unitcost":1,
    "capacity":3000
  },
  "workspeed":100,
  "Nodes":[{
      "y":50,
      "x":50,
      "p":0,
      "id":1,
      "d":0,
      "draft":3001.5,
      "labels":[]
    },{
      "y":66,
      "x":66,
      "p":261,
      "id":2,
      "d":463,
      "draft":11,
      "labels":[]
    },{
      "y":43,
      "x":64,
      "p":270,
      "id":3,
      "d":450,
      "draft":11.5,
      "labels":[]
    },{
      "y":43,
      "x":7,
      "p":513,
      "id":4,
      "d":556,
      "draft":10.5,
      "labels":[]
    },{
      "y":90,
      "x":2,
      "p":566,
      "id":5,
      "d":382,
      "draft":10,
      "labels":[]
    },{
      "y":52,
      "x":20,
      "p":420,
      "id":6,
      "d":353,
      "draft":11.5,
      "labels":[]
    },{
      "y":42,
      "x":7,
      "p":340,
      "id":7,
      "d":477,
      "draft":9.5,
      "labels":[]
    },{
      "y":63,
      "x":55,
      "p":597,
      "id":8,
      "d":564,
      "draft":11,
      "labels":[]
    },{
      "y":42,
      "x":9,
      "p":476,
      "id":9,
      "d":514,
      "draft":10.5,
      "labels":[]
    },{
      "y":54,
      "x":67,
      "p":569,
      "id":10,
      "d":542,
      "draft":10.5,
      "labels":[]
    },{
      "y":71,
      "x":82,
      "p":535,
      "id":11,
      "d":707,
      "draft":10.5,
      "labels":[]
    },{
      "y":87,
      "x":12,
      "p":611,
      "id":12,
      "d":749,
      "draft":11.5,
      "labels":[]
    },{
      "y":87,
      "x":53,
      "p":413,
      "id":13,
      "d":375,
      "draft":11.5,
      "labels":[]
    },{
      "y":66,
      "x":43,
      "p":282,
      "id":14,
      "d":414,
      "draft":11,
      "labels":[]
    },{
      "y":46,
      "x":65,
      "p":629,
      "id":15,
      "d":449,
      "draft":10.5,
      "labels":[]
    },{
      "y":91,
      "x":80,
      "p":708,
      "id":16,
      "d":420,
      "draft":10.5,
      "labels":[]
    }],
  "totaltimelimit":4320,
  "starttime":0
}